avaliacao.v
module principal (
    input e1,
    input e0, 
    input p3, 
    input p2,
    input p1,
    input p0,

//saidas normais
    output y1, 
    output y0, 


//display
    output seg_a,
    output seg_b,
    output seg_c,
    output seg_d,
    output seg_e,
    output seg_f,
    output seg_g


    
);
    reg y1_fio,y0_fio;
     
    reg[6:0] segmentos;

    assign y1 = y1_fio;
    assign y0 = y0_fio;
    assign {seg_a,seg_b,seg_c,seg_d,seg_e,seg_f,seg_g}=segmentos;

    initial begin 
        y1_fio=1'b0;//inicializamos os valores com 0 para nao dar erro de xxxxxxx lixo de memoria 
        y0_fio=1'b0;
        segmentos=7'b0000000;
    end
 always @(*) begin//sensivel a qualquer mudanca de entrada 
        
        
       //bit mais significativo
        y1_fio <= e1 | (~e0 & p3) | (p3 & p2 & ~p1) | (p3 & p2 & ~p0); 
        
        // bit menos significativo
        y0_fio <= (e1 & ~p3) | (e1 & ~p2) | (e1 & p1 & p0) | (~e1 & e0) | (~e1 & p3);
    end


always @(*) begin
 case ({y1_fio, y0_fio}) 
2'b00: segmentos <= 7'b0001100; 

2'b01: segmentos <= 7'b1111010;

2'b10: segmentos  <= 7'b1111100;

2'b11: segmentos <= 7'b1110011;
 endcase
    end

endmodule

avaliacao_tb.v
module principal_tb;
 
    reg e1_in ,e0_in;
    reg p3_in,p2_in,p1_in,p0_in;
    
    wire y1_out,y0_out;
    wire seg_a_out, seg_b_out, seg_c_out, seg_d_out;
    wire seg_e_out, seg_f_out, seg_g_out;

    integer i, j;

    principal DUT (
        .e1(e1_in), .e0(e0_in), .p0(p0_in), .p1(p1_in),
        .p2(p2_in), .p3(p3_in), .y1(y1_out), .y0(y0_out),
        .seg_a(seg_a_out), .seg_b(seg_b_out), .seg_c(seg_c_out),
        .seg_d(seg_d_out), .seg_e(seg_e_out), .seg_f(seg_f_out),
        .seg_g(seg_g_out)
    );

    initial begin
        $dumpfile("simulacao.vcd");
        $dumpvars(0, principal_tb);
    end

    initial begin
        for (i = 0; i < 4; i = i + 1) begin
            for (j = 0; j < 16; j = j + 1) begin
                // O Verilog atribui os bits menos significativos do integer, que é o comportamento desejado.
                {e1_in, e0_in} = i;
                {p3_in, p2_in, p1_in, p0_in} = j;
                
                #10;
            end
        end
 
        #10; 
        $finish;
    end				
endmodule

simulacao.vcd
$date
	Thu Oct 16 11:04:53 2025
$end
$version
	Icarus Verilog
$end
$timescale
	1s
$end
$scope module principal_tb $end
$var wire 1 ! y1_out $end
$var wire 1 " y0_out $end
$var wire 1 # seg_g_out $end
$var wire 1 $ seg_f_out $end
$var wire 1 % seg_e_out $end
$var wire 1 & seg_d_out $end
$var wire 1 ' seg_c_out $end
$var wire 1 ( seg_b_out $end
$var wire 1 ) seg_a_out $end
$var reg 1 * e0_in $end
$var reg 1 + e1_in $end
$var reg 1 , p0_in $end
$var reg 1 - p1_in $end
$var reg 1 . p2_in $end
$var reg 1 / p3_in $end
$var integer 32 0 i [31:0] $end
$var integer 32 1 j [31:0] $end
$scope module DUT $end
$var wire 1 * e0 $end
$var wire 1 + e1 $end
$var wire 1 , p0 $end
$var wire 1 - p1 $end
$var wire 1 . p2 $end
$var wire 1 / p3 $end
$var wire 1 " y0 $end
$var wire 1 ! y1 $end
$var wire 1 # seg_g $end
$var wire 1 $ seg_f $end
$var wire 1 % seg_e $end
$var wire 1 & seg_d $end
$var wire 1 ' seg_c $end
$var wire 1 ( seg_b $end
$var wire 1 ) seg_a $end
$var reg 7 2 segmentos [6:0] $end
$var reg 1 3 y0_fio $end
$var reg 1 4 y1_fio $end
$upscope $end
$upscope $end
$enddefinitions $end
$comment Show the parameter values. $end
$dumpall
$end
#0
$dumpvars
04
03
b1100 2
b0 1
b0 0
0/
0.
0-
0,
0+
0*
0)
0(
0'
1&
1%
0$
0#
0"
0!
$end
#10
1,
b1 1
#20
1-
0,
b10 1
#30
1,
b11 1
#40
1.
0-
0,
b100 1
#50
1,
b101 1
#60
1-
0,
b110 1
#70
1,
b111 1
#80
1)
1(
1'
0&
0%
1$
1#
b1110011 2
1"
13
1!
14
1/
0.
0-
0,
b1000 1
#90
1,
b1001 1
#100
1-
0,
b1010 1
#110
1,
b1011 1
#120
1.
0-
0,
b1100 1
#130
1,
b1101 1
#140
1-
0,
b1110 1
#150
1,
b1111 1
#160
1&
0#
b1111010 2
0!
04
0/
0.
0-
0,
1*
b1 0
b0 1
#170
1,
b1 1
#180
1-
0,
b10 1
#190
1,
b11 1
#200
1.
0-
0,
b100 1
#210
1,
b101 1
#220
1-
0,
b110 1
#230
1,
b111 1
#240
1/
0.
0-
0,
b1000 1
#250
1,
b1001 1
#260
1-
0,
b1010 1
#270
1,
b1011 1
#280
0&
1#
b1110011 2
1!
14
1.
0-
0,
b1100 1
#290
1,
b1101 1
#300
1-
0,
b1110 1
#310
1&
0#
b1111010 2
0!
04
1,
b1111 1
#320
0&
1#
b1110011 2
1!
14
0/
0.
0-
0,
1+
0*
b10 0
b0 1
#330
1,
b1 1
#340
1-
0,
b10 1
#350
1,
b11 1
#360
1.
0-
0,
b100 1
#370
1,
b101 1
#380
1-
0,
b110 1
#390
1,
b111 1
#400
1/
0.
0-
0,
b1000 1
#410
1,
b1001 1
#420
1-
0,
b1010 1
#430
1,
b1011 1
#440
1&
1%
0$
0#
b1111100 2
0"
03
1.
0-
0,
b1100 1
#450
1,
b1101 1
#460
1-
0,
b1110 1
#470
0&
0%
1$
1#
b1110011 2
1"
13
1,
b1111 1
#480
0/
0.
0-
0,
1*
b11 0
b0 1
#490
1,
b1 1
#500
1-
0,
b10 1
#510
1,
b11 1
#520
1.
0-
0,
b100 1
#530
1,
b101 1
#540
1-
0,
b110 1
#550
1,
b111 1
#560
1/
0.
0-
0,
b1000 1
#570
1,
b1001 1
#580
1-
0,
b1010 1
#590
1,
b1011 1
#600
1&
1%
0$
0#
b1111100 2
0"
03
1.
0-
0,
b1100 1
#610
1,
b1101 1
#620
1-
0,
b1110 1
#630
0&
0%
1$
1#
b1110011 2
1"
13
1,
b1111 1
#640
b100 0
b10000 1
